{
  "id": "cashflowpoly-local-env",
  "name": "Cashflowpoly Local Docker",
  "values": [
    {
      "key": "baseUrl",
      "value": "http://localhost:5041",
      "type": "default",
      "enabled": true
    },
    {
      "key": "authUsername",
      "value": "instructor",
      "type": "default",
      "enabled": true
    },
    {
      "key": "authPassword",
      "value": "replace-with-your-password",
      "type": "secret",
      "enabled": true
    },
    {
      "key": "registerUsername",
      "value": "newplayer",
      "type": "default",
      "enabled": true
    },
    {
      "key": "registerPassword",
      "value": "replace-with-player-password",
      "type": "secret",
      "enabled": true
    },
    {
      "key": "accessToken",
      "value": "",
      "type": "default",
      "enabled": true
    },
    {
      "key": "rulesetId",
      "value": "",
      "type": "default",
      "enabled": true
    },
    {
      "key": "sessionId",
      "value": "",
      "type": "default",
      "enabled": true
    },
    {
      "key": "playerId",
      "value": "",
      "type": "default",
      "enabled": true
    }
  ],
  "_postman_variable_scope": "environment",
  "_postman_exported_at": "2026-02-18T00:00:00.000Z",
  "_postman_exported_using": "GitHub Copilot"
}
